{"cameraMode":{"drawMode":0,"name":"Shaded","section":"Shading Mode"},"sceneLighting":true,"audioPlay":false,"sceneViewState":{"m_AlwaysRefresh":false,"showFog":true,"showSkybox":true,"showFlares":true,"showImageEffects":true,"showParticleSystems":true,"showVisualEffectGraphs":true,"m_FxEnabled":true},"in2DMode":false,"pivot":{"x":-1.9031260013580323,"y":4.38633394241333,"z":4.546799182891846},"rotation":{"x":-0.09206801652908325,"y":-0.8990955352783203,"z":0.22891588509082795,"w":-0.3616079092025757},"size":1.2248245477676392,"orthographic":false}